[
  {
    "id": "69631",
    "name": "DABUWARAN PRI. SCH. DABUWARAN  I",
    "registration_area_id": "3820",
    "precise_location": null,
    "abbreviation": "001",
    "units": "001",
    "delimitation": "17/16/03/001",
    "remark": "EXISTING PU",
    "ward_id": "3820",
    "ward_name": "DABUWARAN",
    "local_government_id": "335",
    "local_government_name": "KAUGAMA",
    "state_id": "17",
    "state_name": "JIGAWA",
    "location": {
      "latitude": 12.3889523,
      "longitude": 9.7344154,
      "viewport": {
        "northeast": {
          "lat": 12.4296414,
          "lng": 9.790127199999999
        },
        "southwest": {
          "lat": 12.3541654,
          "lng": 9.6837252
        }
      },
      "formatted_address": "Dabuwaran, 730102, Nigeria",
      "google_map_url": "https://maps.google.com?q=12.3889523,9.7344154",
      "google_place_id": "ChIJFwqZqzEOqRERHowMbYCmraM"
    }
  },
  {
    "id": "69632",
    "name": "DABUWARAN PRI. SCH. DABUWARAN  II",
    "registration_area_id": "3820",
    "precise_location": null,
    "abbreviation": "002",
    "units": "002",
    "delimitation": "17/16/03/002",
    "remark": "EXISTING PU",
    "ward_id": "3820",
    "ward_name": "DABUWARAN",
    "local_government_id": "335",
    "local_government_name": "KAUGAMA",
    "state_id": "17",
    "state_name": "JIGAWA",
    "location": {
      "latitude": 12.3889523,
      "longitude": 9.7344154,
      "viewport": {
        "northeast": {
          "lat": 12.4296414,
          "lng": 9.790127199999999
        },
        "southwest": {
          "lat": 12.3541654,
          "lng": 9.6837252
        }
      },
      "formatted_address": "Dabuwaran, 730102, Nigeria",
      "google_map_url": "https://maps.google.com?q=12.3889523,9.7344154",
      "google_place_id": "ChIJFwqZqzEOqRERHowMbYCmraM"
    }
  },
  {
    "id": "69633",
    "name": "GANGARA PRI. SCH.  GANGARA",
    "registration_area_id": "3820",
    "precise_location": null,
    "abbreviation": "003",
    "units": "003",
    "delimitation": "17/16/03/003",
    "remark": "EXISTING PU",
    "ward_id": "3820",
    "ward_name": "DABUWARAN",
    "local_government_id": "335",
    "local_government_name": "KAUGAMA",
    "state_id": "17",
    "state_name": "JIGAWA",
    "location": {
      "latitude": 12.4506066,
      "longitude": 10.040496,
      "viewport": {
        "northeast": {
          "lat": 12.45195212989272,
          "lng": 10.04183082989272
        },
        "southwest": {
          "lat": 12.44925247010728,
          "lng": 10.03913117010728
        }
      },
      "formatted_address": "10 Maje Rd, 731211, Hadejia, Nigeria",
      "google_map_url": "https://maps.google.com?q=12.4506066,10.040496",
      "google_place_id": "ChIJrf1sGOgWqRERK-FKp9jPu5g"
    }
  },
  {
    "id": "69634",
    "name": "DUSARE PRI. SCH. DUSARE",
    "registration_area_id": "3820",
    "precise_location": null,
    "abbreviation": "004",
    "units": "004",
    "delimitation": "17/16/03/004",
    "remark": "EXISTING PU",
    "ward_id": "3820",
    "ward_name": "DABUWARAN",
    "local_government_id": "335",
    "local_government_name": "KAUGAMA",
    "state_id": "17",
    "state_name": "JIGAWA",
    "location": {
      "latitude": 11.7052553,
      "longitude": 9.3389737,
      "viewport": {
        "northeast": {
          "lat": 11.70660107989272,
          "lng": 9.340284729892723
        },
        "southwest": {
          "lat": 11.70390142010728,
          "lng": 9.337585070107279
        }
      },
      "formatted_address": "P84Q+4H5, 720101, Dutse, Nigeria",
      "google_map_url": "https://maps.google.com?q=11.7052553,9.3389737",
      "google_place_id": "ChIJa1ZhyovxqxERWYfgvdfOW-A"
    }
  },
  {
    "id": "69635",
    "name": "MANDA PRI. SCH. MANDA",
    "registration_area_id": "3820",
    "precise_location": null,
    "abbreviation": "005",
    "units": "005",
    "delimitation": "17/16/03/005",
    "remark": "EXISTING PU",
    "ward_id": "3820",
    "ward_name": "DABUWARAN",
    "local_government_id": "335",
    "local_government_name": "KAUGAMA",
    "state_id": "17",
    "state_name": "JIGAWA",
    "location": {
      "latitude": 12.4506066,
      "longitude": 10.040496,
      "viewport": {
        "northeast": {
          "lat": 12.45195212989272,
          "lng": 10.04183082989272
        },
        "southwest": {
          "lat": 12.44925247010728,
          "lng": 10.03913117010728
        }
      },
      "formatted_address": "10 Maje Rd, 731211, Hadejia, Nigeria",
      "google_map_url": "https://maps.google.com?q=12.4506066,10.040496",
      "google_place_id": "ChIJlZho1TkFqRERQqaMU7Kyieg"
    }
  },
  {
    "id": "69636",
    "name": "SHARKAWA PRI. SCH  SHARKAWA",
    "registration_area_id": "3820",
    "precise_location": null,
    "abbreviation": "006",
    "units": "006",
    "delimitation": "17/16/03/006",
    "remark": "EXISTING PU",
    "ward_id": "3820",
    "ward_name": "DABUWARAN",
    "local_government_id": "335",
    "local_government_name": "KAUGAMA",
    "state_id": "17",
    "state_name": "JIGAWA",
    "location": {
      "latitude": 12.6757669,
      "longitude": 9.2641399,
      "viewport": {
        "northeast": {
          "lat": 12.67714202989272,
          "lng": 9.265466179892721
        },
        "southwest": {
          "lat": 12.67444237010728,
          "lng": 9.262766520107277
        }
      },
      "formatted_address": "M7G7+8J4, 732106, Sule Tankarka, Nigeria",
      "google_map_url": "https://maps.google.com?q=12.6757669,9.2641399",
      "google_place_id": "ChIJ7bPBr8XVqBERLLdpX46-6j0"
    }
  },
  {
    "id": "69637",
    "name": "G/BAGUDU PRI. SCH. GARIN BAGUDU",
    "registration_area_id": "3820",
    "precise_location": null,
    "abbreviation": "007",
    "units": "007",
    "delimitation": "17/16/03/007",
    "remark": "EXISTING PU",
    "ward_id": "3820",
    "ward_name": "DABUWARAN",
    "local_government_id": "335",
    "local_government_name": "KAUGAMA",
    "state_id": "17",
    "state_name": "JIGAWA",
    "location": null
  },
  {
    "id": "69638",
    "name": "IDON ZAKARA",
    "registration_area_id": "3820",
    "precise_location": null,
    "abbreviation": "008",
    "units": "008",
    "delimitation": "17/16/03/008",
    "remark": "EXISTING PU",
    "ward_id": "3820",
    "ward_name": "DABUWARAN",
    "local_government_id": "335",
    "local_government_name": "KAUGAMA",
    "state_id": "17",
    "state_name": "JIGAWA",
    "location": {
      "latitude": 11.5679694,
      "longitude": 9.320734,
      "viewport": {
        "northeast": {
          "lat": 11.56911177989272,
          "lng": 9.322104929892722
        },
        "southwest": {
          "lat": 11.56641212010728,
          "lng": 9.319405270107278
        }
      },
      "formatted_address": "H89C+57Q, Kiyawa Road, 712103, Dutse, Nigeria",
      "google_map_url": "https://maps.google.com?q=11.5679694,9.320734",
      "google_place_id": "ChIJi7V7y9_zqxERyrEFk0ldfbg"
    }
  },
  {
    "id": "69639",
    "name": "MUSARI PRI. SCH.  MUSARI",
    "registration_area_id": "3820",
    "precise_location": null,
    "abbreviation": "009",
    "units": "009",
    "delimitation": "17/16/03/009",
    "remark": "EXISTING PU",
    "ward_id": "3820",
    "ward_name": "DABUWARAN",
    "local_government_id": "335",
    "local_government_name": "KAUGAMA",
    "state_id": "17",
    "state_name": "JIGAWA",
    "location": {
      "latitude": 12.4506066,
      "longitude": 10.040496,
      "viewport": {
        "northeast": {
          "lat": 12.45195212989272,
          "lng": 10.04183082989272
        },
        "southwest": {
          "lat": 12.44925247010728,
          "lng": 10.03913117010728
        }
      },
      "formatted_address": "10 Maje Rd, 731211, Hadejia, Nigeria",
      "google_map_url": "https://maps.google.com?q=12.4506066,10.040496",
      "google_place_id": "ChIJlZho1TkFqRERQqaMU7Kyieg"
    }
  },
  {
    "id": "69640",
    "name": "K/GAMAWA PRI. SCH.  KANWAR  G.",
    "registration_area_id": "3820",
    "precise_location": null,
    "abbreviation": "010",
    "units": "010",
    "delimitation": "17/16/03/010",
    "remark": "EXISTING PU",
    "ward_id": "3820",
    "ward_name": "DABUWARAN",
    "local_government_id": "335",
    "local_government_name": "KAUGAMA",
    "state_id": "17",
    "state_name": "JIGAWA",
    "location": {
      "latitude": 12.0697386,
      "longitude": 8.7669512,
      "viewport": {
        "northeast": {
          "lat": 12.07126067989272,
          "lng": 8.768244529892721
        },
        "southwest": {
          "lat": 12.06856102010728,
          "lng": 8.765544870107277
        }
      },
      "formatted_address": "7F4C3Q98+WQQ K Kanawa Community, Isah Kaita St, Ward 700101, Kano, Nigeria",
      "google_map_url": "https://maps.google.com?q=12.0697386,8.7669512",
      "google_place_id": "ChIJ8zrXAjKZrhERIsoXDKlCN94"
    }
  },
  {
    "id": "69641",
    "name": "JSS DABUWARAN",
    "registration_area_id": "3820",
    "precise_location": null,
    "abbreviation": "011",
    "units": "011",
    "delimitation": "17/16/03/011",
    "remark": "NEW PU",
    "ward_id": "3820",
    "ward_name": "DABUWARAN",
    "local_government_id": "335",
    "local_government_name": "KAUGAMA",
    "state_id": "17",
    "state_name": "JIGAWA",
    "location": {
      "latitude": 11.5679694,
      "longitude": 9.320734,
      "viewport": {
        "northeast": {
          "lat": 11.56911177989272,
          "lng": 9.322104929892722
        },
        "southwest": {
          "lat": 11.56641212010728,
          "lng": 9.319405270107278
        }
      },
      "formatted_address": "H89C+57Q, Kiyawa Road, 712103, Dutse, Nigeria",
      "google_map_url": "https://maps.google.com?q=11.5679694,9.320734",
      "google_place_id": "ChIJi7V7y9_zqxERyrEFk0ldfbg"
    }
  },
  {
    "id": "69642",
    "name": "DUSARE PRI SCH. II",
    "registration_area_id": "3820",
    "precise_location": null,
    "abbreviation": "012",
    "units": "012",
    "delimitation": "17/16/03/012",
    "remark": "NEW PU",
    "ward_id": "3820",
    "ward_name": "DABUWARAN",
    "local_government_id": "335",
    "local_government_name": "KAUGAMA",
    "state_id": "17",
    "state_name": "JIGAWA",
    "location": {
      "latitude": 12.1594066,
      "longitude": 8.6033894,
      "viewport": {
        "northeast": {
          "lat": 12.16079262989272,
          "lng": 8.604730779892721
        },
        "southwest": {
          "lat": 12.15809297010728,
          "lng": 8.602031120107277
        }
      },
      "formatted_address": "7F4C5J53+P9C School, 702103, Minjibir, Nigeria",
      "google_map_url": "https://maps.google.com?q=12.1594066,8.6033894",
      "google_place_id": "ChIJ6UZKwEePrhEReDSqT8_vOO8"
    }
  },
  {
    "id": "69643",
    "name": "TSAMIYA GOMA PLAY GROUND",
    "registration_area_id": "3820",
    "precise_location": null,
    "abbreviation": "013",
    "units": "013",
    "delimitation": "17/16/03/013",
    "remark": "NEW PU",
    "ward_id": "3820",
    "ward_name": "DABUWARAN",
    "local_government_id": "335",
    "local_government_name": "KAUGAMA",
    "state_id": "17",
    "state_name": "JIGAWA",
    "location": {
      "latitude": 12.4764498,
      "longitude": 9.7380516,
      "viewport": {
        "northeast": {
          "lat": 12.47780867989272,
          "lng": 9.739409529892722
        },
        "southwest": {
          "lat": 12.47510902010728,
          "lng": 9.736709870107278
        }
      },
      "formatted_address": "FPGQ+H6F, Qtrs 730102, Abasha, Nigeria",
      "google_map_url": "https://maps.google.com?q=12.4764498,9.7380516",
      "google_place_id": "ChIJqQf51K4FqRERL5vNbYCOMx8"
    }
  },
  {
    "id": "69644",
    "name": "MUSARAN TA FULANI P/G",
    "registration_area_id": "3820",
    "precise_location": null,
    "abbreviation": "014",
    "units": "014",
    "delimitation": "17/16/03/014",
    "remark": "NEW PU",
    "ward_id": "3820",
    "ward_name": "DABUWARAN",
    "local_government_id": "335",
    "local_government_name": "KAUGAMA",
    "state_id": "17",
    "state_name": "JIGAWA",
    "location": null
  }
]