[
  {
    "id": "54799",
    "name": "TOWN HALL / ILE ONIKUN & ILE OWA",
    "registration_area_id": "2959",
    "precise_location": null,
    "abbreviation": "001",
    "units": "001",
    "delimitation": "13/15/08/001",
    "remark": "EXISTING PU",
    "ward_id": "2959",
    "ward_name": "IKUN I",
    "local_government_id": "257",
    "local_government_name": "MOBA",
    "state_id": "13",
    "state_name": "EKITI",
    "location": {
      "latitude": 40.8298459,
      "longitude": -73.9444758,
      "viewport": {
        "northeast": {
          "lat": 40.83115032989272,
          "lng": -73.94315947010729
        },
        "southwest": {
          "lat": 40.82845067010727,
          "lng": -73.94585912989272
        }
      },
      "formatted_address": "1867 Amsterdam Ave, New York, NY 10031, United States",
      "google_map_url": "https://maps.google.com?q=40.8298459,-73.9444758",
      "google_place_id": "ChIJDyH_j4f2wokR0IpUGRa9yQg"
    }
  },
  {
    "id": "54800",
    "name": "INF. OF OBALEYE'S HOUSE / OKE ILOTIN & ODO ILOTIN",
    "registration_area_id": "2959",
    "precise_location": null,
    "abbreviation": "002",
    "units": "002",
    "delimitation": "13/15/08/002",
    "remark": "EXISTING PU",
    "ward_id": "2959",
    "ward_name": "IKUN I",
    "local_government_id": "257",
    "local_government_name": "MOBA",
    "state_id": "13",
    "state_name": "EKITI",
    "location": {
      "latitude": 8.4378169,
      "longitude": 4.516297499999999,
      "viewport": {
        "northeast": {
          "lat": 8.43905687989272,
          "lng": 4.517534979892721
        },
        "southwest": {
          "lat": 8.436357220107276,
          "lng": 4.514835320107277
        }
      },
      "formatted_address": "CGQ8+4GF, 240281, Ilorin, Nigeria",
      "google_map_url": "https://maps.google.com?q=8.4378169,4.516297499999999",
      "google_place_id": "ChIJY-u5dN6sNxARB__0RifCiII"
    }
  },
  {
    "id": "54801",
    "name": "S.D.A PRY SCH. / ODO ISAWO & EHIN AGBARA",
    "registration_area_id": "2959",
    "precise_location": null,
    "abbreviation": "003",
    "units": "003",
    "delimitation": "13/15/08/003",
    "remark": "EXISTING PU",
    "ward_id": "2959",
    "ward_name": "IKUN I",
    "local_government_id": "257",
    "local_government_name": "MOBA",
    "state_id": "13",
    "state_name": "EKITI",
    "location": {
      "latitude": -6.6529341,
      "longitude": 147.0000207,
      "viewport": {
        "northeast": {
          "lat": -6.651484720107279,
          "lng": 147.0011960298927
        },
        "southwest": {
          "lat": -6.654184379892722,
          "lng": 146.9984963701073
        }
      },
      "formatted_address": "82W2+R2C, Lae, Papua New Guinea",
      "google_map_url": "https://maps.google.com?q=-6.6529341,147.0000207",
      "google_place_id": "ChIJSWY5YoUD-mgRu4CRgpaLAW4"
    }
  },
  {
    "id": "54802",
    "name": "TOWN HALL  / ILE AKOGILEDE",
    "registration_area_id": "2959",
    "precise_location": null,
    "abbreviation": "004",
    "units": "004",
    "delimitation": "13/15/08/004",
    "remark": "EXISTING PU",
    "ward_id": "2959",
    "ward_name": "IKUN I",
    "local_government_id": "257",
    "local_government_name": "MOBA",
    "state_id": "13",
    "state_name": "EKITI",
    "location": null
  },
  {
    "id": "54803",
    "name": "ADEGBAYI'S HOUSE / IGBO EPA & IDI AFA",
    "registration_area_id": "2959",
    "precise_location": null,
    "abbreviation": "005",
    "units": "005",
    "delimitation": "13/15/08/005",
    "remark": "EXISTING PU",
    "ward_id": "2959",
    "ward_name": "IKUN I",
    "local_government_id": "257",
    "local_government_name": "MOBA",
    "state_id": "13",
    "state_name": "EKITI",
    "location": {
      "latitude": 6.614533499999999,
      "longitude": 3.3592156,
      "viewport": {
        "northeast": {
          "lat": 6.615865629892722,
          "lng": 3.360539229892722
        },
        "southwest": {
          "lat": 6.613165970107278,
          "lng": 3.357839570107278
        }
      },
      "formatted_address": "Lasepa Building The Secretariat, Governor's Rd, Alausa 101233, Lagos, Nigeria",
      "google_map_url": "https://maps.google.com?q=6.614533499999999,3.3592156",
      "google_place_id": "ChIJK3LK-bWTOxARAY1aSbbt0tg"
    }
  },
  {
    "id": "54804",
    "name": "A.U.D / C.A UNITED / ARAROMI",
    "registration_area_id": "2959",
    "precise_location": null,
    "abbreviation": "006",
    "units": "006",
    "delimitation": "13/15/08/006",
    "remark": "EXISTING PU",
    "ward_id": "2959",
    "ward_name": "IKUN I",
    "local_government_id": "257",
    "local_government_name": "MOBA",
    "state_id": "13",
    "state_name": "EKITI",
    "location": null
  },
  {
    "id": "54805",
    "name": "A.U.D / C.A UNITED / NEW MARKET AREA",
    "registration_area_id": "2959",
    "precise_location": null,
    "abbreviation": "007",
    "units": "007",
    "delimitation": "13/15/08/007",
    "remark": "EXISTING PU",
    "ward_id": "2959",
    "ward_name": "IKUN I",
    "local_government_id": "257",
    "local_government_name": "MOBA",
    "state_id": "13",
    "state_name": "EKITI",
    "location": null
  }
]