[
  {
    "id": "339885",
    "name": "OKE ATA HOUSING EST  I",
    "registration_area_id": "17278",
    "precise_location": null,
    "abbreviation": "001",
    "units": "001",
    "delimitation": "27/01/16/001",
    "remark": "EXISTING PU",
    "ward_id": "17278",
    "ward_name": "IBARA ORILE/ONISASA",
    "local_government_id": "562",
    "local_government_name": "ABEOKUTA NORTH",
    "state_id": "27",
    "state_name": "OGUN",
    "location": {
      "latitude": 7.136828,
      "longitude": 3.2912978,
      "viewport": {
        "northeast": {
          "lat": 7.138148429892722,
          "lng": 3.292645229892722
        },
        "southwest": {
          "lat": 7.135448770107278,
          "lng": 3.289945570107277
        }
      },
      "formatted_address": "47PR+PGM, 111105, Abeokuta, Nigeria",
      "google_map_url": "https://maps.google.com?q=7.136828,3.2912978",
      "google_place_id": "ChIJnZYf6LxNOhARW3wzrlEQkkQ"
    }
  },
  {
    "id": "339886",
    "name": "OKE ATA HOUSING EST  II",
    "registration_area_id": "17278",
    "precise_location": null,
    "abbreviation": "002",
    "units": "002",
    "delimitation": "27/01/16/002",
    "remark": "EXISTING PU",
    "ward_id": "17278",
    "ward_name": "IBARA ORILE/ONISASA",
    "local_government_id": "562",
    "local_government_name": "ABEOKUTA NORTH",
    "state_id": "27",
    "state_name": "OGUN",
    "location": {
      "latitude": 7.136828,
      "longitude": 3.2912978,
      "viewport": {
        "northeast": {
          "lat": 7.138148429892722,
          "lng": 3.292645229892722
        },
        "southwest": {
          "lat": 7.135448770107278,
          "lng": 3.289945570107277
        }
      },
      "formatted_address": "47PR+PGM, 111105, Abeokuta, Nigeria",
      "google_map_url": "https://maps.google.com?q=7.136828,3.2912978",
      "google_place_id": "ChIJnZYf6LxNOhARW3wzrlEQkkQ"
    }
  },
  {
    "id": "339887",
    "name": "ST. LUKES IBARA ORILE I",
    "registration_area_id": "17278",
    "precise_location": null,
    "abbreviation": "003",
    "units": "003",
    "delimitation": "27/01/16/003",
    "remark": "EXISTING PU",
    "ward_id": "17278",
    "ward_name": "IBARA ORILE/ONISASA",
    "local_government_id": "562",
    "local_government_name": "ABEOKUTA NORTH",
    "state_id": "27",
    "state_name": "OGUN",
    "location": {
      "latitude": 7.140017400000001,
      "longitude": 3.2527054,
      "viewport": {
        "northeast": {
          "lat": 7.1426151,
          "lng": 3.2570069
        },
        "southwest": {
          "lat": 7.134042999999999,
          "lng": 3.2438509
        }
      },
      "formatted_address": "110103, Ibara Orile, Nigeria",
      "google_map_url": "https://maps.google.com?q=7.140017400000001,3.2527054",
      "google_place_id": "ChIJDWSyD2xSOhARadUTwOyOJm0"
    }
  },
  {
    "id": "339888",
    "name": "ST. LUKES IBARA ORILE II",
    "registration_area_id": "17278",
    "precise_location": null,
    "abbreviation": "004",
    "units": "004",
    "delimitation": "27/01/16/004",
    "remark": "EXISTING PU",
    "ward_id": "17278",
    "ward_name": "IBARA ORILE/ONISASA",
    "local_government_id": "562",
    "local_government_name": "ABEOKUTA NORTH",
    "state_id": "27",
    "state_name": "OGUN",
    "location": {
      "latitude": 7.140017400000001,
      "longitude": 3.2527054,
      "viewport": {
        "northeast": {
          "lat": 7.1426151,
          "lng": 3.2570069
        },
        "southwest": {
          "lat": 7.134042999999999,
          "lng": 3.2438509
        }
      },
      "formatted_address": "110103, Ibara Orile, Nigeria",
      "google_map_url": "https://maps.google.com?q=7.140017400000001,3.2527054",
      "google_place_id": "ChIJDWSyD2xSOhARadUTwOyOJm0"
    }
  },
  {
    "id": "339889",
    "name": "NEAR SURAKAT MOSQUE",
    "registration_area_id": "17278",
    "precise_location": null,
    "abbreviation": "005",
    "units": "005",
    "delimitation": "27/01/16/005",
    "remark": "EXISTING PU",
    "ward_id": "17278",
    "ward_name": "IBARA ORILE/ONISASA",
    "local_government_id": "562",
    "local_government_name": "ABEOKUTA NORTH",
    "state_id": "27",
    "state_name": "OGUN",
    "location": {
      "latitude": 7.1463627,
      "longitude": 3.352756,
      "viewport": {
        "northeast": {
          "lat": 7.147468729892721,
          "lng": 3.354338179892722
        },
        "southwest": {
          "lat": 7.144769070107277,
          "lng": 3.351638520107278
        }
      },
      "formatted_address": "49W3+G4R, Isabo 111102, Abeokuta, Nigeria",
      "google_map_url": "https://maps.google.com?q=7.1463627,3.352756",
      "google_place_id": "ChIJCS1Vv-xLOhARWgLe1QNs0-Q"
    }
  },
  {
    "id": "339890",
    "name": "NEAR MAMMY MARKET ALAMALA",
    "registration_area_id": "17278",
    "precise_location": null,
    "abbreviation": "006",
    "units": "006",
    "delimitation": "27/01/16/006",
    "remark": "EXISTING PU",
    "ward_id": "17278",
    "ward_name": "IBARA ORILE/ONISASA",
    "local_government_id": "562",
    "local_government_name": "ABEOKUTA NORTH",
    "state_id": "27",
    "state_name": "OGUN",
    "location": {
      "latitude": 6.8640244,
      "longitude": 3.6703764,
      "viewport": {
        "northeast": {
          "lat": 6.865414679892721,
          "lng": 3.671712179892721
        },
        "southwest": {
          "lat": 6.862715020107277,
          "lng": 3.669012520107278
        }
      },
      "formatted_address": "Unnamed Road, 121102, Nigeria",
      "google_map_url": "https://maps.google.com?q=6.8640244,3.6703764",
      "google_place_id": "ChIJJ7qlgNfZOxAReAA-0_kveh8"
    }
  },
  {
    "id": "339891",
    "name": "A.N.L.G. IDIYA",
    "registration_area_id": "17278",
    "precise_location": null,
    "abbreviation": "007",
    "units": "007",
    "delimitation": "27/01/16/007",
    "remark": "EXISTING PU",
    "ward_id": "17278",
    "ward_name": "IBARA ORILE/ONISASA",
    "local_government_id": "562",
    "local_government_name": "ABEOKUTA NORTH",
    "state_id": "27",
    "state_name": "OGUN",
    "location": {
      "latitude": 7.1824621,
      "longitude": 3.2819659,
      "viewport": {
        "northeast": {
          "lat": 7.183906279892721,
          "lng": 3.283356579892722
        },
        "southwest": {
          "lat": 7.181206620107277,
          "lng": 3.280656920107277
        }
      },
      "formatted_address": "6FV557JJ+XQP, 16 Idiya Rd, 111105, Abeokuta, Nigeria",
      "google_map_url": "https://maps.google.com?q=7.1824621,3.2819659",
      "google_place_id": "ChIJ10s7MWdPOhAR-AXgRzxb9aQ"
    }
  },
  {
    "id": "339892",
    "name": "ONISASA VILLAGE",
    "registration_area_id": "17278",
    "precise_location": null,
    "abbreviation": "008",
    "units": "008",
    "delimitation": "27/01/16/008",
    "remark": "EXISTING PU",
    "ward_id": "17278",
    "ward_name": "IBARA ORILE/ONISASA",
    "local_government_id": "562",
    "local_government_name": "ABEOKUTA NORTH",
    "state_id": "27",
    "state_name": "OGUN",
    "location": {
      "latitude": 7.1783715,
      "longitude": 3.2483058,
      "viewport": {
        "northeast": {
          "lat": 7.2873466,
          "lng": 3.307584
        },
        "southwest": {
          "lat": 7.067643599999999,
          "lng": 3.1928937
        }
      },
      "formatted_address": "Ibara Orile/Onisasa, Nigeria",
      "google_map_url": "https://maps.google.com?q=7.1783715,3.2483058",
      "google_place_id": "ChIJt9Yl2_pROhAR7Qqa0eXBPeI"
    }
  },
  {
    "id": "339893",
    "name": "ST. JOHN'S SCHOOL IDI-ORI",
    "registration_area_id": "17278",
    "precise_location": null,
    "abbreviation": "009",
    "units": "009",
    "delimitation": "27/01/16/009",
    "remark": "EXISTING PU",
    "ward_id": "17278",
    "ward_name": "IBARA ORILE/ONISASA",
    "local_government_id": "562",
    "local_government_name": "ABEOKUTA NORTH",
    "state_id": "27",
    "state_name": "OGUN",
    "location": {
      "latitude": 7.112776999999999,
      "longitude": 3.274648,
      "viewport": {
        "northeast": {
          "lat": 7.114147379892722,
          "lng": 3.276029429892722
        },
        "southwest": {
          "lat": 7.111447720107278,
          "lng": 3.273329770107277
        }
      },
      "formatted_address": "6FV5477F+3RJ Ikereku 16, Idiori, Nigeria",
      "google_map_url": "https://maps.google.com?q=7.112776999999999,3.274648",
      "google_place_id": "ChIJ1S3PqxBNOhARp-2C6w5pZPo"
    }
  },
  {
    "id": "339894",
    "name": "ILUGUN VILLAGE",
    "registration_area_id": "17278",
    "precise_location": null,
    "abbreviation": "010",
    "units": "010",
    "delimitation": "27/01/16/010",
    "remark": "EXISTING PU",
    "ward_id": "17278",
    "ward_name": "IBARA ORILE/ONISASA",
    "local_government_id": "562",
    "local_government_name": "ABEOKUTA NORTH",
    "state_id": "27",
    "state_name": "OGUN",
    "location": {
      "latitude": 7.176334799999999,
      "longitude": 3.3451886,
      "viewport": {
        "northeast": {
          "lat": 7.1802066,
          "lng": 3.3502378
        },
        "southwest": {
          "lat": 7.1739781,
          "lng": 3.341069
        }
      },
      "formatted_address": "Ilugun 110101, Abeokuta, Nigeria",
      "google_map_url": "https://maps.google.com?q=7.176334799999999,3.3451886",
      "google_place_id": "ChIJ25kf21FJOhARZsGZBROov4E"
    }
  },
  {
    "id": "339895",
    "name": "COMMUNITY PRI.SCH. IBARO",
    "registration_area_id": "17278",
    "precise_location": null,
    "abbreviation": "011",
    "units": "011",
    "delimitation": "27/01/16/011",
    "remark": "EXISTING PU",
    "ward_id": "17278",
    "ward_name": "IBARA ORILE/ONISASA",
    "local_government_id": "562",
    "local_government_name": "ABEOKUTA NORTH",
    "state_id": "27",
    "state_name": "OGUN",
    "location": {
      "latitude": 7.141037,
      "longitude": 3.33933,
      "viewport": {
        "northeast": {
          "lat": 7.142469229892722,
          "lng": 3.340815129892722
        },
        "southwest": {
          "lat": 7.139769570107278,
          "lng": 3.338115470107277
        }
      },
      "formatted_address": "6FV548RQ+CP8, Community 14, Ibara 111102, Abeokuta, Nigeria",
      "google_map_url": "https://maps.google.com?q=7.141037,3.33933",
      "google_place_id": "ChIJ5cZFihBLOhARvt-DWB7G414"
    }
  },
  {
    "id": "339896",
    "name": "ADELEYE VILLAGE",
    "registration_area_id": "17278",
    "precise_location": null,
    "abbreviation": "012",
    "units": "012",
    "delimitation": "27/01/16/012",
    "remark": "EXISTING PU",
    "ward_id": "17278",
    "ward_name": "IBARA ORILE/ONISASA",
    "local_government_id": "562",
    "local_government_name": "ABEOKUTA NORTH",
    "state_id": "27",
    "state_name": "OGUN",
    "location": {
      "latitude": 7.1783715,
      "longitude": 3.2483058,
      "viewport": {
        "northeast": {
          "lat": 7.2873466,
          "lng": 3.307584
        },
        "southwest": {
          "lat": 7.067643599999999,
          "lng": 3.1928937
        }
      },
      "formatted_address": "Ibara Orile/Onisasa, Nigeria",
      "google_map_url": "https://maps.google.com?q=7.1783715,3.2483058",
      "google_place_id": "ChIJt9Yl2_pROhAR7Qqa0eXBPeI"
    }
  },
  {
    "id": "339897",
    "name": "ISALE ISOLO",
    "registration_area_id": "17278",
    "precise_location": null,
    "abbreviation": "013",
    "units": "013",
    "delimitation": "27/01/16/013",
    "remark": "EXISTING PU",
    "ward_id": "17278",
    "ward_name": "IBARA ORILE/ONISASA",
    "local_government_id": "562",
    "local_government_name": "ABEOKUTA NORTH",
    "state_id": "27",
    "state_name": "OGUN",
    "location": {
      "latitude": 7.1783715,
      "longitude": 3.2483058,
      "viewport": {
        "northeast": {
          "lat": 7.2873466,
          "lng": 3.307584
        },
        "southwest": {
          "lat": 7.067643599999999,
          "lng": 3.1928937
        }
      },
      "formatted_address": "Ibara Orile/Onisasa, Nigeria",
      "google_map_url": "https://maps.google.com?q=7.1783715,3.2483058",
      "google_place_id": "ChIJt9Yl2_pROhAR7Qqa0eXBPeI"
    }
  },
  {
    "id": "339898",
    "name": "ISALE BAALE",
    "registration_area_id": "17278",
    "precise_location": null,
    "abbreviation": "014",
    "units": "014",
    "delimitation": "27/01/16/014",
    "remark": "EXISTING PU",
    "ward_id": "17278",
    "ward_name": "IBARA ORILE/ONISASA",
    "local_government_id": "562",
    "local_government_name": "ABEOKUTA NORTH",
    "state_id": "27",
    "state_name": "OGUN",
    "location": {
      "latitude": 7.1783715,
      "longitude": 3.2483058,
      "viewport": {
        "northeast": {
          "lat": 7.2873466,
          "lng": 3.307584
        },
        "southwest": {
          "lat": 7.067643599999999,
          "lng": 3.1928937
        }
      },
      "formatted_address": "Ibara Orile/Onisasa, Nigeria",
      "google_map_url": "https://maps.google.com?q=7.1783715,3.2483058",
      "google_place_id": "ChIJt9Yl2_pROhAR7Qqa0eXBPeI"
    }
  },
  {
    "id": "339899",
    "name": "IDI-IGBA VILLAGE",
    "registration_area_id": "17278",
    "precise_location": null,
    "abbreviation": "015",
    "units": "015",
    "delimitation": "27/01/16/015",
    "remark": "EXISTING PU",
    "ward_id": "17278",
    "ward_name": "IBARA ORILE/ONISASA",
    "local_government_id": "562",
    "local_government_name": "ABEOKUTA NORTH",
    "state_id": "27",
    "state_name": "OGUN",
    "location": {
      "latitude": 7.1783715,
      "longitude": 3.2483058,
      "viewport": {
        "northeast": {
          "lat": 7.2873466,
          "lng": 3.307584
        },
        "southwest": {
          "lat": 7.067643599999999,
          "lng": 3.1928937
        }
      },
      "formatted_address": "Ibara Orile/Onisasa, Nigeria",
      "google_map_url": "https://maps.google.com?q=7.1783715,3.2483058",
      "google_place_id": "ChIJt9Yl2_pROhAR7Qqa0eXBPeI"
    }
  },
  {
    "id": "339900",
    "name": "AFRICAN SCH. ELEFUN OSILE",
    "registration_area_id": "17278",
    "precise_location": null,
    "abbreviation": "016",
    "units": "016",
    "delimitation": "27/01/16/016",
    "remark": "EXISTING PU",
    "ward_id": "17278",
    "ward_name": "IBARA ORILE/ONISASA",
    "local_government_id": "562",
    "local_government_name": "ABEOKUTA NORTH",
    "state_id": "27",
    "state_name": "OGUN",
    "location": {
      "latitude": 7.142401,
      "longitude": 3.328809,
      "viewport": {
        "northeast": {
          "lat": 7.143849379892722,
          "lng": 3.330152429892722
        },
        "southwest": {
          "lat": 7.141149720107278,
          "lng": 3.327452770107277
        }
      },
      "formatted_address": "12, 6FV548RH+XG7 north Ogun, Ita Eko 111102, Abeokuta, Nigeria",
      "google_map_url": "https://maps.google.com?q=7.142401,3.328809",
      "google_place_id": "ChIJi4J5dnJMOhART6z7fnQOkxs"
    }
  },
  {
    "id": "339901",
    "name": "ST. JOSEPH RCM NUR/PRY SCHOOL OLUWO VILLAGE",
    "registration_area_id": "17278",
    "precise_location": null,
    "abbreviation": "017",
    "units": "017",
    "delimitation": "27/01/16/017",
    "remark": "NEW PU",
    "ward_id": "17278",
    "ward_name": "IBARA ORILE/ONISASA",
    "local_government_id": "562",
    "local_government_name": "ABEOKUTA NORTH",
    "state_id": "27",
    "state_name": "OGUN",
    "location": {
      "latitude": 7.136024,
      "longitude": 3.3268786,
      "viewport": {
        "northeast": {
          "lat": 7.137373829892722,
          "lng": 3.328228429892722
        },
        "southwest": {
          "lat": 7.134674170107278,
          "lng": 3.325528770107278
        }
      },
      "formatted_address": "30 Quarry Rd, Ibara 111102, Abeokuta, Nigeria",
      "google_map_url": "https://maps.google.com?q=7.136024,3.3268786",
      "google_place_id": "ChIJtVc1iLxNOhARszJVnNVdGT4"
    }
  },
  {
    "id": "339902",
    "name": "OPEN SPACE IN FRONT OF PROPOSED HEALTH CENTER ILE-ISE AWO",
    "registration_area_id": "17278",
    "precise_location": null,
    "abbreviation": "018",
    "units": "018",
    "delimitation": "27/01/16/018",
    "remark": "NEW PU",
    "ward_id": "17278",
    "ward_name": "IBARA ORILE/ONISASA",
    "local_government_id": "562",
    "local_government_name": "ABEOKUTA NORTH",
    "state_id": "27",
    "state_name": "OGUN",
    "location": {
      "latitude": 7.1205257,
      "longitude": 3.2939775,
      "viewport": {
        "northeast": {
          "lat": 7.121773879892722,
          "lng": 3.295308579892722
        },
        "southwest": {
          "lat": 7.119074220107279,
          "lng": 3.292608920107277
        }
      },
      "formatted_address": "47CV+6H9, Surulere Idi Ori., Abeokuta, Nigeria",
      "google_map_url": "https://maps.google.com?q=7.1205257,3.2939775",
      "google_place_id": "ChIJC9TFNgFNOhARAZoMKVPQ0g8"
    }
  },
  {
    "id": "339903",
    "name": "OPEN SPACE AT OLORUNSOGO ADIO , SOYOYE",
    "registration_area_id": "17278",
    "precise_location": null,
    "abbreviation": "019",
    "units": "019",
    "delimitation": "27/01/16/019",
    "remark": "NEW PU",
    "ward_id": "17278",
    "ward_name": "IBARA ORILE/ONISASA",
    "local_government_id": "562",
    "local_government_name": "ABEOKUTA NORTH",
    "state_id": "27",
    "state_name": "OGUN",
    "location": {
      "latitude": 7.149849499999999,
      "longitude": 3.3668951,
      "viewport": {
        "northeast": {
          "lat": 7.151147929892721,
          "lng": 3.368202429892722
        },
        "southwest": {
          "lat": 7.148448270107277,
          "lng": 3.365502770107277
        }
      },
      "formatted_address": "no 9 .siji koku avenue .olorunsogo., Idi-aba, Abeokuta, Nigeria",
      "google_map_url": "https://maps.google.com?q=7.149849499999999,3.3668951",
      "google_place_id": "ChIJGQJjY8ZLOhARTVuI3rA6-1A"
    }
  },
  {
    "id": "339904",
    "name": "OPEN SPACE AT ILUPEJU IDIYA JUNCTION, IDIYA",
    "registration_area_id": "17278",
    "precise_location": null,
    "abbreviation": "020",
    "units": "020",
    "delimitation": "27/01/16/020",
    "remark": "NEW PU",
    "ward_id": "17278",
    "ward_name": "IBARA ORILE/ONISASA",
    "local_government_id": "562",
    "local_government_name": "ABEOKUTA NORTH",
    "state_id": "27",
    "state_name": "OGUN",
    "location": null
  },
  {
    "id": "339905",
    "name": ".A.N.L.G NURSERY AND PRIMARY SCHOOL, ADIO AJEGUNLE SOYOYE.",
    "registration_area_id": "17278",
    "precise_location": null,
    "abbreviation": "021",
    "units": "021",
    "delimitation": "27/01/16/021",
    "remark": "NEW PU",
    "ward_id": "17278",
    "ward_name": "IBARA ORILE/ONISASA",
    "local_government_id": "562",
    "local_government_name": "ABEOKUTA NORTH",
    "state_id": "27",
    "state_name": "OGUN",
    "location": {
      "latitude": 7.141057000000001,
      "longitude": 3.326557,
      "viewport": {
        "northeast": {
          "lat": 7.142477629892722,
          "lng": 3.327918829892723
        },
        "southwest": {
          "lat": 7.139777970107279,
          "lng": 3.325219170107278
        }
      },
      "formatted_address": "48RG+CJM, Ajegunle Adio soyoye, Abeokuta, Nigeria",
      "google_map_url": "https://maps.google.com?q=7.141057000000001,3.326557",
      "google_place_id": "ChIJgxJ0hw1NOhARQ96rW5d1On8"
    }
  },
  {
    "id": "339906",
    "name": "OPEN SPACE AT TRANSFORMER JUNCTION, TUNDE SODIPO ESTATE, GREENFIELD ROUND",
    "registration_area_id": "17278",
    "precise_location": null,
    "abbreviation": "022",
    "units": "022",
    "delimitation": "27/01/16/022",
    "remark": "NEW PU",
    "ward_id": "17278",
    "ward_name": "IBARA ORILE/ONISASA",
    "local_government_id": "562",
    "local_government_name": "ABEOKUTA NORTH",
    "state_id": "27",
    "state_name": "OGUN",
    "location": null
  },
  {
    "id": "339907",
    "name": "NEAR ISALE OLA COMMINITY HALL, SOYOYE",
    "registration_area_id": "17278",
    "precise_location": null,
    "abbreviation": "023",
    "units": "023",
    "delimitation": "27/01/16/023",
    "remark": "NEW PU",
    "ward_id": "17278",
    "ward_name": "IBARA ORILE/ONISASA",
    "local_government_id": "562",
    "local_government_name": "ABEOKUTA NORTH",
    "state_id": "27",
    "state_name": "OGUN",
    "location": {
      "latitude": 7.149849499999999,
      "longitude": 3.3668951,
      "viewport": {
        "northeast": {
          "lat": 7.151147929892721,
          "lng": 3.368202429892722
        },
        "southwest": {
          "lat": 7.148448270107277,
          "lng": 3.365502770107277
        }
      },
      "formatted_address": "no 9 .siji koku avenue .olorunsogo., Idi-aba, Abeokuta, Nigeria",
      "google_map_url": "https://maps.google.com?q=7.149849499999999,3.3668951",
      "google_place_id": "ChIJGQJjY8ZLOhARTVuI3rA6-1A"
    }
  },
  {
    "id": "339908",
    "name": "OPEN SPACE IN FRONT OF ORIOLA COMMINITY HALL, SOYOYE",
    "registration_area_id": "17278",
    "precise_location": null,
    "abbreviation": "024",
    "units": "024",
    "delimitation": "27/01/16/024",
    "remark": "NEW PU",
    "ward_id": "17278",
    "ward_name": "IBARA ORILE/ONISASA",
    "local_government_id": "562",
    "local_government_name": "ABEOKUTA NORTH",
    "state_id": "27",
    "state_name": "OGUN",
    "location": {
      "latitude": 7.167261799999999,
      "longitude": 3.3031045,
      "viewport": {
        "northeast": {
          "lat": 7.16858707989272,
          "lng": 3.304549679892722
        },
        "southwest": {
          "lat": 7.165887420107277,
          "lng": 3.301850020107278
        }
      },
      "formatted_address": "GATEWAY RADIO HOUSE, 111105, Abeokuta, Nigeria",
      "google_map_url": "https://maps.google.com?q=7.167261799999999,3.3031045",
      "google_place_id": "ChIJVzFm_YFOOhARmLlh3XEbe1w"
    }
  },
  {
    "id": "339909",
    "name": "OPEN SPACE IN FRONT OF COMMUNITY HALL, IDI-ORI",
    "registration_area_id": "17278",
    "precise_location": null,
    "abbreviation": "025",
    "units": "025",
    "delimitation": "27/01/16/025",
    "remark": "NEW PU",
    "ward_id": "17278",
    "ward_name": "IBARA ORILE/ONISASA",
    "local_government_id": "562",
    "local_government_name": "ABEOKUTA NORTH",
    "state_id": "27",
    "state_name": "OGUN",
    "location": {
      "latitude": 7.1205257,
      "longitude": 3.2939775,
      "viewport": {
        "northeast": {
          "lat": 7.121773879892722,
          "lng": 3.295308579892722
        },
        "southwest": {
          "lat": 7.119074220107279,
          "lng": 3.292608920107277
        }
      },
      "formatted_address": "47CV+6H9, Surulere Idi Ori., Abeokuta, Nigeria",
      "google_map_url": "https://maps.google.com?q=7.1205257,3.2939775",
      "google_place_id": "ChIJC9TFNgFNOhARAZoMKVPQ0g8"
    }
  },
  {
    "id": "339910",
    "name": "OPEN SPACE IN FRONT OF COMMUNITY HEALTH CENTRE, ADEUN",
    "registration_area_id": "17278",
    "precise_location": null,
    "abbreviation": "026",
    "units": "026",
    "delimitation": "27/01/16/026",
    "remark": "NEW PU",
    "ward_id": "17278",
    "ward_name": "IBARA ORILE/ONISASA",
    "local_government_id": "562",
    "local_government_name": "ABEOKUTA NORTH",
    "state_id": "27",
    "state_name": "OGUN",
    "location": {
      "latitude": 7.1747611,
      "longitude": 3.2901052,
      "viewport": {
        "northeast": {
          "lat": 7.176036629892724,
          "lng": 3.291388279892722
        },
        "southwest": {
          "lat": 7.17333697010728,
          "lng": 3.288688620107278
        }
      },
      "formatted_address": "Klm 4 Abeokuta-imeko, expressway, Adeun, Abeokuta, Nigeria",
      "google_map_url": "https://maps.google.com?q=7.1747611,3.2901052",
      "google_place_id": "ChIJzzMGaClPOhARth0aWz3YNFc"
    }
  },
  {
    "id": "339911",
    "name": "OPEN SPACE AT MERCY LAND ESTATE, ADEUN",
    "registration_area_id": "17278",
    "precise_location": null,
    "abbreviation": "027",
    "units": "027",
    "delimitation": "27/01/16/027",
    "remark": "NEW PU",
    "ward_id": "17278",
    "ward_name": "IBARA ORILE/ONISASA",
    "local_government_id": "562",
    "local_government_name": "ABEOKUTA NORTH",
    "state_id": "27",
    "state_name": "OGUN",
    "location": {
      "latitude": 7.1758904,
      "longitude": 3.2968869,
      "viewport": {
        "northeast": {
          "lat": 7.177091029892722,
          "lng": 3.298253179892723
        },
        "southwest": {
          "lat": 7.174391370107278,
          "lng": 3.295553520107278
        }
      },
      "formatted_address": "Mercyland Estate, 4 flat, Adeun, Abeokuta, Nigeria",
      "google_map_url": "https://maps.google.com?q=7.1758904,3.2968869",
      "google_place_id": "ChIJW6LynP1POhARwNuZcyf0iRM"
    }
  },
  {
    "id": "339912",
    "name": "A.N.L.G NURSERY AND PRIMARY SCHOOL, MANGO OKE ATA.",
    "registration_area_id": "17278",
    "precise_location": null,
    "abbreviation": "028",
    "units": "028",
    "delimitation": "27/01/16/028",
    "remark": "NEW PU",
    "ward_id": "17278",
    "ward_name": "IBARA ORILE/ONISASA",
    "local_government_id": "562",
    "local_government_name": "ABEOKUTA NORTH",
    "state_id": "27",
    "state_name": "OGUN",
    "location": {
      "latitude": 7.1707356,
      "longitude": 3.2693435,
      "viewport": {
        "northeast": {
          "lat": 7.172073629892722,
          "lng": 3.270710029892722
        },
        "southwest": {
          "lat": 7.169373970107278,
          "lng": 3.268010370107278
        }
      },
      "formatted_address": "Soyoye, 111105, Abeokuta, Nigeria",
      "google_map_url": "https://maps.google.com?q=7.1707356,3.2693435",
      "google_place_id": "ChIJSx4qgG1POhARGqR8oTBouI8"
    }
  }
]