[
  {
    "id": "19039",
    "name": "S/BIRNI EAST",
    "abbreviation": "01",
    "local_government_id": "711",
    "local_government_name": "S/BIRNI",
    "state_id": "33",
    "state_name": "SOKOTO"
  },
  {
    "id": "19040",
    "name": "S/BIRNI WEST",
    "abbreviation": "02",
    "local_government_id": "711",
    "local_government_name": "S/BIRNI",
    "state_id": "33",
    "state_name": "SOKOTO"
  },
  {
    "id": "19041",
    "name": "TSAMAYE",
    "abbreviation": "03",
    "local_government_id": "711",
    "local_government_name": "S/BIRNI",
    "state_id": "33",
    "state_name": "SOKOTO"
  },
  {
    "id": "19042",
    "name": "UNGUWAR LALLE",
    "abbreviation": "04",
    "local_government_id": "711",
    "local_government_name": "S/BIRNI",
    "state_id": "33",
    "state_name": "SOKOTO"
  },
  {
    "id": "19043",
    "name": "TARA",
    "abbreviation": "05",
    "local_government_id": "711",
    "local_government_name": "S/BIRNI",
    "state_id": "33",
    "state_name": "SOKOTO"
  },
  {
    "id": "19044",
    "name": "GATAWA",
    "abbreviation": "06",
    "local_government_id": "711",
    "local_government_name": "S/BIRNI",
    "state_id": "33",
    "state_name": "SOKOTO"
  },
  {
    "id": "19045",
    "name": "KURAWA",
    "abbreviation": "07",
    "local_government_id": "711",
    "local_government_name": "S/BIRNI",
    "state_id": "33",
    "state_name": "SOKOTO"
  },
  {
    "id": "19046",
    "name": "GANGARA",
    "abbreviation": "08",
    "local_government_id": "711",
    "local_government_name": "S/BIRNI",
    "state_id": "33",
    "state_name": "SOKOTO"
  },
  {
    "id": "19047",
    "name": "KALGO",
    "abbreviation": "09",
    "local_government_id": "711",
    "local_government_name": "S/BIRNI",
    "state_id": "33",
    "state_name": "SOKOTO"
  },
  {
    "id": "19048",
    "name": "MAKUWANA",
    "abbreviation": "10",
    "local_government_id": "711",
    "local_government_name": "S/BIRNI",
    "state_id": "33",
    "state_name": "SOKOTO"
  },
  {
    "id": "19049",
    "name": "LAJINGE",
    "abbreviation": "11",
    "local_government_id": "711",
    "local_government_name": "S/BIRNI",
    "state_id": "33",
    "state_name": "SOKOTO"
  }
]