[
  {
    "id": "376662",
    "name": "BUBA, KOFAR BUBA",
    "registration_area_id": "19255",
    "precise_location": null,
    "abbreviation": "001",
    "units": "001",
    "delimitation": "34/10/07/001",
    "remark": "EXISTING PU",
    "ward_id": "19255",
    "ward_name": "KUNINI",
    "local_government_id": "731",
    "local_government_name": "LAU",
    "state_id": "34",
    "state_name": "TARABA",
    "location": null
  },
  {
    "id": "376663",
    "name": "BUBA GEDE, DEVT. AREA OFFICE",
    "registration_area_id": "19255",
    "precise_location": null,
    "abbreviation": "002",
    "units": "002",
    "delimitation": "34/10/07/002",
    "remark": "EXISTING PU",
    "ward_id": "19255",
    "ward_name": "KUNINI",
    "local_government_id": "731",
    "local_government_name": "LAU",
    "state_id": "34",
    "state_name": "TARABA",
    "location": null
  },
  {
    "id": "376664",
    "name": "GARIN SARKI I, G/SARKI PRIMARY SCHOOL",
    "registration_area_id": "19255",
    "precise_location": null,
    "abbreviation": "003",
    "units": "003",
    "delimitation": "34/10/07/003",
    "remark": "EXISTING PU",
    "ward_id": "19255",
    "ward_name": "KUNINI",
    "local_government_id": "731",
    "local_government_name": "LAU",
    "state_id": "34",
    "state_name": "TARABA",
    "location": null
  },
  {
    "id": "376665",
    "name": "GARIN SARKI II, G/SARKI PRIMARY SCHOOL",
    "registration_area_id": "19255",
    "precise_location": null,
    "abbreviation": "004",
    "units": "004",
    "delimitation": "34/10/07/004",
    "remark": "EXISTING PU",
    "ward_id": "19255",
    "ward_name": "KUNINI",
    "local_government_id": "731",
    "local_government_name": "LAU",
    "state_id": "34",
    "state_name": "TARABA",
    "location": null
  },
  {
    "id": "376666",
    "name": "JAURO TUKUR KOFAR JAURO TUKUR",
    "registration_area_id": "19255",
    "precise_location": null,
    "abbreviation": "005",
    "units": "005",
    "delimitation": "34/10/07/005",
    "remark": "EXISTING PU",
    "ward_id": "19255",
    "ward_name": "KUNINI",
    "local_government_id": "731",
    "local_government_name": "LAU",
    "state_id": "34",
    "state_name": "TARABA",
    "location": null
  },
  {
    "id": "376667",
    "name": "KUNINI PRIMARY SCHOOL, KUNINI PRIMARY SCHOOL",
    "registration_area_id": "19255",
    "precise_location": null,
    "abbreviation": "006",
    "units": "006",
    "delimitation": "34/10/07/006",
    "remark": "EXISTING PU",
    "ward_id": "19255",
    "ward_name": "KUNINI",
    "local_government_id": "731",
    "local_government_name": "LAU",
    "state_id": "34",
    "state_name": "TARABA",
    "location": null
  },
  {
    "id": "376668",
    "name": "MAISAJE, KOFAR MAISAJE",
    "registration_area_id": "19255",
    "precise_location": null,
    "abbreviation": "007",
    "units": "007",
    "delimitation": "34/10/07/007",
    "remark": "EXISTING PU",
    "ward_id": "19255",
    "ward_name": "KUNINI",
    "local_government_id": "731",
    "local_government_name": "LAU",
    "state_id": "34",
    "state_name": "TARABA",
    "location": null
  },
  {
    "id": "376669",
    "name": "RUNDE, RUNDE",
    "registration_area_id": "19255",
    "precise_location": null,
    "abbreviation": "008",
    "units": "008",
    "delimitation": "34/10/07/008",
    "remark": "EXISTING PU",
    "ward_id": "19255",
    "ward_name": "KUNINI",
    "local_government_id": "731",
    "local_government_name": "LAU",
    "state_id": "34",
    "state_name": "TARABA",
    "location": null
  },
  {
    "id": "376670",
    "name": "KOFAR BUBA II, KUNINI NORTHPRIMARY SCHOOL,",
    "registration_area_id": "19255",
    "precise_location": null,
    "abbreviation": "009",
    "units": "009",
    "delimitation": "34/10/07/009",
    "remark": "NEW PU",
    "ward_id": "19255",
    "ward_name": "KUNINI",
    "local_government_id": "731",
    "local_government_name": "LAU",
    "state_id": "34",
    "state_name": "TARABA",
    "location": null
  },
  {
    "id": "376671",
    "name": "BUBA GEDE II, DEVT.AREA OFFICE",
    "registration_area_id": "19255",
    "precise_location": null,
    "abbreviation": "010",
    "units": "010",
    "delimitation": "34/10/07/010",
    "remark": "NEW PU",
    "ward_id": "19255",
    "ward_name": "KUNINI",
    "local_government_id": "731",
    "local_government_name": "LAU",
    "state_id": "34",
    "state_name": "TARABA",
    "location": null
  },
  {
    "id": "376672",
    "name": "KANAWA I,KANAWA TUDUPRIMARY SCHOOL",
    "registration_area_id": "19255",
    "precise_location": null,
    "abbreviation": "011",
    "units": "011",
    "delimitation": "34/10/07/011",
    "remark": "NEW PU",
    "ward_id": "19255",
    "ward_name": "KUNINI",
    "local_government_id": "731",
    "local_government_name": "LAU",
    "state_id": "34",
    "state_name": "TARABA",
    "location": null
  },
  {
    "id": "376673",
    "name": "G/SARKIN III, G/SARKIN DISPENSARY CLINIC",
    "registration_area_id": "19255",
    "precise_location": null,
    "abbreviation": "012",
    "units": "012",
    "delimitation": "34/10/07/012",
    "remark": "NEW PU",
    "ward_id": "19255",
    "ward_name": "KUNINI",
    "local_government_id": "731",
    "local_government_name": "LAU",
    "state_id": "34",
    "state_name": "TARABA",
    "location": null
  },
  {
    "id": "376674",
    "name": "KARMUKE,KARMUKE PRIMARY SCHOOL",
    "registration_area_id": "19255",
    "precise_location": null,
    "abbreviation": "013",
    "units": "013",
    "delimitation": "34/10/07/013",
    "remark": "NEW PU",
    "ward_id": "19255",
    "ward_name": "KUNINI",
    "local_government_id": "731",
    "local_government_name": "LAU",
    "state_id": "34",
    "state_name": "TARABA",
    "location": null
  },
  {
    "id": "376675",
    "name": "JAURO TUKUR II, KUNINI DISPENSARY CLINIC",
    "registration_area_id": "19255",
    "precise_location": null,
    "abbreviation": "014",
    "units": "014",
    "delimitation": "34/10/07/014",
    "remark": "NEW PU",
    "ward_id": "19255",
    "ward_name": "KUNINI",
    "local_government_id": "731",
    "local_government_name": "LAU",
    "state_id": "34",
    "state_name": "TARABA",
    "location": null
  },
  {
    "id": "376676",
    "name": "KUNINI II, KUNINI MOTOR PARK",
    "registration_area_id": "19255",
    "precise_location": null,
    "abbreviation": "015",
    "units": "015",
    "delimitation": "34/10/07/015",
    "remark": "NEW PU",
    "ward_id": "19255",
    "ward_name": "KUNINI",
    "local_government_id": "731",
    "local_government_name": "LAU",
    "state_id": "34",
    "state_name": "TARABA",
    "location": null
  },
  {
    "id": "376677",
    "name": "KUNINI III,GDSS KUNINI",
    "registration_area_id": "19255",
    "precise_location": null,
    "abbreviation": "016",
    "units": "016",
    "delimitation": "34/10/07/016",
    "remark": "NEW PU",
    "ward_id": "19255",
    "ward_name": "KUNINI",
    "local_government_id": "731",
    "local_government_name": "LAU",
    "state_id": "34",
    "state_name": "TARABA",
    "location": null
  },
  {
    "id": "376678",
    "name": "KOFAR MAI SAJE II KUNINI II PRIMARY SCHOOL",
    "registration_area_id": "19255",
    "precise_location": null,
    "abbreviation": "017",
    "units": "017",
    "delimitation": "34/10/07/017",
    "remark": "NEW PU",
    "ward_id": "19255",
    "ward_name": "KUNINI",
    "local_government_id": "731",
    "local_government_name": "LAU",
    "state_id": "34",
    "state_name": "TARABA",
    "location": null
  }
]